{
  "tests": [
    {
      "targets": ["unit_tests"],
      "profiles": ["Debug"]
    },
    {
      "targets": ["stress_tests"],
      "profiles": [
        "FaultyFibers",
        "Debug",
        "FaultyThreadsASan",
        "FaultyThreadsTSan"
      ]
    }
  ],
  "lint_files": ["condvar.hpp"],
  "submit_files": ["condvar.hpp"],
  "forbidden": [
    {
      "patterns": [
        "yield",
        "sleep_for",
        "SpinWait"
      ],
      "files": ["condvar.hpp"],
      "hint": "Use twist::ed::Wait"
    },
    {
      "patterns": [
        "twist/ed/stdlike/mutex.hpp"
      ],
      "hint": "Implement your own mutex"
    }
  ]
}
